setup.py
actadiurna/__init__.py
actadiurna/cli.py
actadiurna.egg-info/PKG-INFO
actadiurna.egg-info/SOURCES.txt
actadiurna.egg-info/dependency_links.txt
actadiurna.egg-info/entry_points.txt
actadiurna.egg-info/top_level.txt