Metadata-Version: 1.1
Name: actadiurna
Version: 0.0.3
Summary: Acta Diurna is a tool for updating /etc/motd
Home-page: https://github.com/unixorn/acta-diurna
Author: Joe Block
Author-email: jpb@unixorn.net
License: UNKNOWN
Download-URL: https://github.com/unixorn/acta-diurna/tarball/0.0.3
Platform: UNKNOWN
